fmo/__init__.py
fmo/logging.py
fmo/main.py
fmo/py.typed
fmo/utils/__init__.py
fmo/utils/dataset.py
fmo/utils/format.py
fmo/utils/version.py
friendli_model_optimizer-0.10.0.dist-info/LICENSE
friendli_model_optimizer-0.10.0.dist-info/METADATA
friendli_model_optimizer-0.10.0.dist-info/WHEEL
friendli_model_optimizer-0.10.0.dist-info/entry_points.txt
friendli_model_optimizer-0.10.0.dist-info/top_level.txt
friendli_model_optimizer-0.10.0.dist-info/RECORD
