Metadata-Version: 2.1
Name: friendli-model-optimizer
Version: 0.10.0
Summary: Model Optimizer CLI for Friendli Engine.
Author-email: FriendliAI teams <eng@friendli.ai>
Project-URL: Homepage, https://friendli.ai/
Project-URL: Repository, https://github.com/friendliai/friendli-model-optimizer
Project-URL: Documentation, https://docs.friendli.ai/
Project-URL: Issues, https://github.com/friendliai/friendli-model-optimizer/issues/new/choose
Keywords: generative-ai,llm,quantization
Classifier: Intended Audience :: Developers
Classifier: Intended Audience :: Education
Classifier: Intended Audience :: Science/Research
Classifier: License :: OSI Approved :: Apache Software License
Classifier: Operating System :: OS Independent
Classifier: Programming Language :: Python :: 3
Classifier: Programming Language :: Python :: 3.9
Classifier: Programming Language :: Python :: 3.10
Classifier: Programming Language :: Python :: 3.11
Classifier: Programming Language :: Python :: 3.12
Classifier: Programming Language :: Python :: 3.13
Classifier: Topic :: Scientific/Engineering :: Artificial Intelligence
Requires-Python: <3.14,>=3.9
License-File: LICENSE
Requires-Dist: transformers>=4.47.1
Requires-Dist: datasets
Requires-Dist: typer
Requires-Dist: torch>=2.0.0
Requires-Dist: accelerate
Requires-Dist: fmo-core==0.10
Provides-Extra: dev
Requires-Dist: black; extra == "dev"
Requires-Dist: isort; extra == "dev"
Requires-Dist: mypy; extra == "dev"
Requires-Dist: pydocstyle; extra == "dev"
Requires-Dist: pylint; extra == "dev"
Requires-Dist: tox; extra == "dev"
Provides-Extra: test
Requires-Dist: black; extra == "test"
Requires-Dist: isort; extra == "test"
Requires-Dist: mypy; extra == "test"
Requires-Dist: pydocstyle; extra == "test"
Requires-Dist: pylint; extra == "test"
Requires-Dist: tox; extra == "test"
Requires-Dist: pytest; extra == "test"
Requires-Dist: pytest-cov; extra == "test"
Requires-Dist: pytest-xdist; extra == "test"
Requires-Dist: coverage; extra == "test"
